fastemail/__init__.py
fastemail/sender.py
fastemail-0.0.1.dist-info/LICENSE
fastemail-0.0.1.dist-info/METADATA
fastemail-0.0.1.dist-info/WHEEL
fastemail-0.0.1.dist-info/top_level.txt
fastemail-0.0.1.dist-info/RECORD
